algbench/__init__.py
algbench/_stream_utils.py
algbench/benchmark.py
algbench/benchmark_db.py
algbench/environment.py
algbench/fingerprint.py
algbench/log_capture.py
algbench/pandas.py
algbench/db/__init__.py
algbench/db/json_serializer.py
algbench/db/nfs_json_dict.py
algbench/db/nfs_json_list.py
algbench/db/nfs_json_set.py
algbench/utils/__init__.py
algbench/utils/timer.py
AlgBench-2.4.1.dist-info/LICENSE
AlgBench-2.4.1.dist-info/METADATA
AlgBench-2.4.1.dist-info/WHEEL
AlgBench-2.4.1.dist-info/top_level.txt
AlgBench-2.4.1.dist-info/RECORD
