Metadata-Version: 2.1
Name: AlgBench
Version: 2.4.1
Summary: Util for benchmarking algorithms.
Author-email: "TU Braunschweig, IBR, Algorithms Group (Dominik Krupke)" <krupke@ibr.cs.tu-bs.de>
Project-URL: Homepage, https://github.com/d-krupke/AlgBench
Project-URL: Issues, https://github.com/d-krupke/AlgBench/issues
Classifier: Programming Language :: Python :: 3
Classifier: License :: OSI Approved :: MIT License
Classifier: Development Status :: 3 - Alpha
Requires-Python: >=3.8
License-File: LICENSE
Requires-Dist: PyYAML >=6.0
Requires-Dist: pandas >=2.0
Requires-Dist: setuptools >=45
